eeo/__init__.py
eeo/common.py
eeo/analysis/__init__.py
eeo/analysis/indices.py
eeo/analysis/indices.pyi
eeo/analysis/stats.py
eeo/analysis/stats.pyi
eeo/core/__init__.py
eeo/core/core.py
eeo/core/core.pyi
eeo/core/decorators.py
eeo/core/loader.py
eeo/core/loader.pyi
eeo/core/plugins.py
eeo/core/types.py
eeo/core/adapters/__init__.py
eeo/core/adapters/base.py
eeo/core/adapters/numpy.py
eeo/core/adapters/rasterio.py
eeo/ops/__init__.py
eeo/ops/algebra.py
eeo/ops/algebra.pyi
eeo/ops/merge.py
eeo/ops/merge.pyi
eeo/preprocessing/__init__.py
eeo/preprocessing/clip.py
eeo/preprocessing/clip.pyi
eeo/preprocessing/normalize.py
eeo/preprocessing/normalize.pyi
eeo/preprocessing/reproject.py
eeo/preprocessing/reproject.pyi
eeo/preprocessing/resample.py
eeo/preprocessing/resample.pyi
eeo/viz/__init__.py
eeo/viz/plot.py
eeo/viz/plot.pyi
easy_eo-0.1.0.dist-info/METADATA
easy_eo-0.1.0.dist-info/WHEEL
easy_eo-0.1.0.dist-info/licenses/LICENSE
easy_eo-0.1.0.dist-info/RECORD
