Metadata-Version: 2.4
Name: easy-eo
Version: 0.1.0
Summary: A lightweight Earth Observation utilities library for chainable raster operations
Project-URL: Homepage, https://github.com/tommy-burns/easy-eo
Project-URL: Repository, https://github.com/tommy-burns/easy-eo
Project-URL: Documentation, https://easy-eo.readthedocs.io
Project-URL: Issues, https://github.com/tommy-burns/easy-eo/issues
Author: Thomas Burns Botchwey
License: MIT License
License-File: LICENSE
Keywords: earth observation,gis,raster,remote sensing
Classifier: Development Status :: 3 - Alpha
Classifier: Intended Audience :: Science/Research
Classifier: License :: OSI Approved :: MIT License
Classifier: Programming Language :: Python :: 3
Classifier: Programming Language :: Python :: 3.10
Classifier: Programming Language :: Python :: 3.11
Classifier: Programming Language :: Python :: 3.12
Classifier: Topic :: Scientific/Engineering :: GIS
Requires-Python: >=3.10
Requires-Dist: geopandas<1.2,>=1.1
Requires-Dist: matplotlib<3.11,>=3.10
Requires-Dist: numpy<2.2,>=1.26
Requires-Dist: rasterio<1.5,>=1.4
